PyTexturePacker/ImageRect.py
PyTexturePacker/Packer.py
PyTexturePacker/Rect.py
PyTexturePacker/Utils.py
PyTexturePacker/__init__.py
PyTexturePacker/GuillotinePacker/GuillotineAtlas.py
PyTexturePacker/GuillotinePacker/GuillotinePacker.py
PyTexturePacker/GuillotinePacker/__init__.py
PyTexturePacker/MaxRectsPacker/MaxRectsAtlas.py
PyTexturePacker/MaxRectsPacker/MaxRectsPacker.py
PyTexturePacker/MaxRectsPacker/__init__.py
PyTexturePacker/PackerInterface/AtlasInterface.py
PyTexturePacker/PackerInterface/PackerInterface.py
PyTexturePacker/PackerInterface/__init__.py
PyTexturePacker-1.2.0.dist-info/LICENSE.txt
PyTexturePacker-1.2.0.dist-info/METADATA
PyTexturePacker-1.2.0.dist-info/WHEEL
PyTexturePacker-1.2.0.dist-info/top_level.txt
PyTexturePacker-1.2.0.dist-info/RECORD
