Metadata-Version: 2.1
Name: PyTexturePacker
Version: 1.2.0
Summary: an package to create sprite sheets or sprite atlases
Home-page: https://github.com/wo1fsea/PyTexturePacker
Download-URL: https://github.com/wo1fsea/PyTexturePacker/releases/tag/v1.2.0
Author: Quanyong Huang
Author-email: quanyongh@foxmail.com
License: MIT
Keywords: TexturePacker,cocos2d-x,sprite-sheet,texture-pack
Classifier: Programming Language :: Python :: 2
Classifier: Programming Language :: Python :: 2.7
Classifier: Programming Language :: Python :: 3
Classifier: Programming Language :: Python :: 3.7
Classifier: Programming Language :: Python :: 3.8
Classifier: Programming Language :: Python :: 3.9
Classifier: Programming Language :: Python :: 3.10
Classifier: Programming Language :: Python :: 3.11
Classifier: Programming Language :: Python :: 3.12
Classifier: Programming Language :: Python :: Implementation :: PyPy
Classifier: Topic :: Multimedia :: Graphics
Classifier: License :: OSI Approved :: MIT License
Classifier: Operating System :: OS Independent
License-File: LICENSE.txt
Requires-Dist: Pillow
